foo_proj/__init__.py
foo_proj/__main__.py
foo_proj/names.txt
foo_proj/speaker.py
foo_proj/speakers/__init__.py
foo_proj/speakers/james.py
foo_proj-0.3.0.dist-info/licenses/LICENSE.txt
foo_proj-0.3.0.dist-info/METADATA
foo_proj-0.3.0.dist-info/WHEEL
foo_proj-0.3.0.dist-info/entry_points.txt
foo_proj-0.3.0.dist-info/top_level.txt
foo_proj-0.3.0.dist-info/RECORD
