Metadata-Version: 2.4
Name: foo_proj
Version: 0.3.0
Summary: My first package!
Author-email: James Hartnert <jameshartnett@comcast.net>
Maintainer-email: James Hartnert <jameshartnett@comcast.net>
License: its all yours
Keywords: James
Classifier: Programming Language :: Python :: 3.9
Classifier: Programming Language :: Python :: Implementation :: CPython
Classifier: License :: OSI Approved :: BSD License
Classifier: Intended Audience :: Developers
Classifier: Operating System :: POSIX :: Linux
Classifier: Operating System :: Microsoft :: Windows
Classifier: Operating System :: MacOS
Classifier: Operating System :: MacOS :: MacOS X
Requires-Python: >=3.9
License-File: LICENSE.txt
Requires-Dist: colorama~=0.0
Provides-Extra: dev
Requires-Dist: twine; extra == "dev"
Requires-Dist: build; extra == "dev"
Dynamic: license-file
